[
  {
    "__TYPE__": "SharedSliceContent",
    "variation": "default",
    "primary": {
      "rich_text": {
        "__TYPE__": "StructuredTextContent",
        "value": [
          {
            "type": "paragraph",
            "content": {
              "text": "Occaecat eiusmod eu magna officia cupidatat in duis cupidatat pariatur elit ex aute officia."
            }
          }
        ]
      }
    },
    "items": [
      {
        "__TYPE__": "GroupItemContent",
        "value": []
      }
    ]
  }
]