{
  "title": {
    "__TYPE__": "StructuredTextContent",
    "value": [
      {
        "type": "heading1",
        "content": {
          "text": "Gasoline"
        }
      }
    ]
  },
  "slices": {
    "__TYPE__": "SliceContentType",
    "value": [
      {
        "key": "hero_banner$f5243f1f-f1ce-43f4-a2b1-700c4cf74706",
        "name": "hero_banner",
        "widget": {
          "__TYPE__": "SharedSliceContent",
          "variation": "default",
          "primary": {
            "title": {
              "__TYPE__": "StructuredTextContent",
              "value": [
                {
                  "type": "heading1",
                  "content": {
                    "text": "Charge"
                  }
                }
              ]
            },
            "description": {
              "__TYPE__": "StructuredTextContent",
              "value": [
                {
                  "type": "paragraph",
                  "content": {
                    "text": "Sint ut laboris velit est deserunt. Pariatur ea occaecat ut sit mollit irure nulla sit. Non anim quis occaecat."
                  }
                }
              ]
            },
            "image": {
              "__TYPE__": "ImageContent",
              "origin": {
                "id": "main",
                "url": "https://images.unsplash.com/photo-1541807084-5c52b6b3adef",
                "width": 4000,
                "height": 6000
              },
              "url": "https://images.unsplash.com/photo-1541807084-5c52b6b3adef",
              "width": 4000,
              "height": 6000,
              "edit": {
                "zoom": 1,
                "crop": {
                  "x": 0,
                  "y": 0
                },
                "background": "transparent"
              },
              "thumbnails": {}
            },
            "button_label": {
              "__TYPE__": "FieldContent",
              "value": "mail",
              "type": "Text"
            },
            "button_link": {
              "__TYPE__": "LinkContent",
              "value": {
                "__TYPE__": "ExternalLink",
                "url": "https://prismic.io"
              }
            }
          },
          "items": [
            {
              "__TYPE__": "GroupItemContent",
              "value": []
            }
          ]
        }
      },
      {
        "key": "banner$1d06d65a-e5ca-4d14-b2b4-a5dc9eb27777",
        "name": "banner",
        "widget": {
          "__TYPE__": "SharedSliceContent",
          "variation": "default",
          "primary": {
            "title": {
              "__TYPE__": "StructuredTextContent",
              "value": [
                {
                  "type": "heading1",
                  "content": {
                    "text": "Excitement"
                  }
                }
              ]
            },
            "sub_title": {
              "__TYPE__": "StructuredTextContent",
              "value": [
                {
                  "type": "paragraph",
                  "content": {
                    "text": "Est in id occaecat officia elit enim sunt laborum duis. Velit cillum ad laboris ex commodo fugiat excepteur cillum sunt adipisicing. Aliquip nulla consequat officia amet qui commodo velit laboris velit."
                  }
                }
              ]
            },
            "description": {
              "__TYPE__": "StructuredTextContent",
              "value": [
                {
                  "type": "paragraph",
                  "content": {
                    "text": "Dolore tempor id sunt officia veniam do Lorem mollit."
                  }
                }
              ]
            },
            "button_link": {
              "__TYPE__": "LinkContent",
              "value": {
                "__TYPE__": "ExternalLink",
                "url": "https://slicemachine.dev"
              }
            },
            "button_label": {
              "__TYPE__": "FieldContent",
              "value": "heavy",
              "type": "Text"
            },
            "image": {
              "__TYPE__": "ImageContent",
              "origin": {
                "id": "main",
                "url": "https://images.unsplash.com/photo-1589321599763-d66926c29613",
                "width": 3168,
                "height": 4752
              },
              "url": "https://images.unsplash.com/photo-1589321599763-d66926c29613",
              "width": 3168,
              "height": 4752,
              "edit": {
                "zoom": 1,
                "crop": {
                  "x": 0,
                  "y": 0
                },
                "background": "transparent"
              },
              "thumbnails": {}
            }
          },
          "items": [
            {
              "__TYPE__": "GroupItemContent",
              "value": []
            }
          ]
        }
      },
      {
        "key": "section_poerty$bdffddfe-62c8-466f-8d47-ff3334e7914b",
        "name": "section_poerty",
        "widget": {
          "__TYPE__": "SharedSliceContent",
          "variation": "default",
          "primary": {
            "title": {
              "__TYPE__": "StructuredTextContent",
              "value": [
                {
                  "type": "heading1",
                  "content": {
                    "text": "Sudden"
                  }
                }
              ]
            },
            "description": {
              "__TYPE__": "StructuredTextContent",
              "value": [
                {
                  "type": "paragraph",
                  "content": {
                    "text": "Eiusmod amet est qui enim veniam anim labore voluptate occaecat reprehenderit culpa tempor ut. Consectetur ea sint laboris aliquip adipisicing reprehenderit mollit cupidatat ullamco. Cillum ad laboris enim occaecat tempor officia nulla ea."
                  }
                }
              ]
            },
            "image": {
              "__TYPE__": "ImageContent",
              "origin": {
                "id": "main",
                "url": "https://images.unsplash.com/photo-1587905069134-008460d7a636",
                "width": 3935,
                "height": 5894
              },
              "url": "https://images.unsplash.com/photo-1587905069134-008460d7a636",
              "width": 3935,
              "height": 5894,
              "edit": {
                "zoom": 1,
                "crop": {
                  "x": 0,
                  "y": 0
                },
                "background": "transparent"
              },
              "thumbnails": {}
            },
            "caption": {
              "__TYPE__": "StructuredTextContent",
              "value": [
                {
                  "type": "paragraph",
                  "content": {
                    "text": "Proident non et quis cillum anim mollit. Consequat id duis pariatur."
                  }
                }
              ]
            },
            "button_label": {
              "__TYPE__": "FieldContent",
              "value": "house",
              "type": "Text"
            },
            "button_link": {
              "__TYPE__": "LinkContent",
              "value": {
                "__TYPE__": "ExternalLink",
                "url": "https://prismic.io"
              }
            }
          },
          "items": [
            {
              "__TYPE__": "GroupItemContent",
              "value": []
            }
          ]
        }
      }
    ]
  }
}