{
  "title": {
    "__TYPE__": "StructuredTextContent",
    "value": [
      {
        "type": "paragraph",
        "content": {
          "text": "Ad culpa velit laboris minim sit sint adipisicing. Deserunt incididunt labore reprehenderit fugiat Lorem cillum velit voluptate minim incididunt eiusmod pariatur veniam irure officia."
        }
      }
    ]
  },
  "uid": {
    "__TYPE__": "UIDContent",
    "value": "reader"
  },
  "date": {
    "__TYPE__": "FieldContent",
    "type": "Date",
    "value": "2015-07-03"
  },
  "excerpt": {
    "__TYPE__": "StructuredTextContent",
    "value": [
      {
        "type": "paragraph",
        "content": {
          "text": "Irure cupidatat consectetur occaecat eu nulla eiusmod laborum amet eu consectetur. Ex ad anim ullamco."
        }
      }
    ]
  },
  "prev": {
    "__TYPE__": "LinkContent",
    "value": {
      "__TYPE__": "ExternalLink",
      "url": "https://slicemachine.dev"
    }
  },
  "next": {
    "__TYPE__": "LinkContent",
    "value": {
      "__TYPE__": "ExternalLink",
      "url": "http://google.com"
    }
  },
  "slices": {
    "__TYPE__": "SliceContentType",
    "value": [
      {
        "key": "code_box$ac4c1781-105c-46fc-89f5-2ef17d6ed939",
        "name": "code_box",
        "widget": {
          "__TYPE__": "SharedSliceContent",
          "variation": "default",
          "primary": {
            "languaje": {
              "__TYPE__": "FieldContent",
              "value": "CSS",
              "type": "Select"
            },
            "code_snippet": {
              "__TYPE__": "StructuredTextContent",
              "value": [
                {
                  "type": "paragraph",
                  "content": {
                    "text": "Consequat exercitation ut est labore pariatur labore tempor ut culpa ad. Duis pariatur Lorem velit mollit id ipsum nulla aute do excepteur est consequat consequat cillum exercitation."
                  }
                }
              ]
            }
          },
          "items": [
            {
              "__TYPE__": "GroupItemContent",
              "value": []
            }
          ]
        }
      },
      {
        "key": "rich_text$6343e8d1-52f7-43be-bdf1-f6baf7a901f2",
        "name": "rich_text",
        "widget": {
          "__TYPE__": "SharedSliceContent",
          "variation": "default",
          "primary": {
            "rich_text": {
              "__TYPE__": "StructuredTextContent",
              "value": [
                {
                  "type": "paragraph",
                  "content": {
                    "text": "Ad ad adipisicing aute ut consequat sint laboris mollit. Cillum consectetur minim tempor ipsum laborum commodo est mollit ex sit. Nulla do nostrud ipsum non enim."
                  }
                }
              ]
            }
          },
          "items": [
            {
              "__TYPE__": "GroupItemContent",
              "value": []
            }
          ]
        }
      },
      {
        "key": "highlighted$fbdff901-a5f3-4736-9f28-10ef1394e519",
        "name": "highlighted",
        "widget": {
          "__TYPE__": "SharedSliceContent",
          "variation": "default",
          "primary": {
            "title": {
              "__TYPE__": "StructuredTextContent",
              "value": [
                {
                  "type": "heading1",
                  "content": {
                    "text": "Experience"
                  }
                }
              ]
            },
            "description": {
              "__TYPE__": "StructuredTextContent",
              "value": [
                {
                  "type": "paragraph",
                  "content": {
                    "text": "Commodo reprehenderit mollit nisi pariatur exercitation veniam eu Lorem. Excepteur culpa deserunt quis. Velit ex culpa Lorem eiusmod labore."
                  }
                }
              ]
            }
          },
          "items": [
            {
              "__TYPE__": "GroupItemContent",
              "value": []
            }
          ]
        }
      },
      {
        "key": "iframe$6686e096-3da8-4047-b30c-a4b02ebb697b",
        "name": "iframe",
        "widget": {
          "__TYPE__": "SharedSliceContent",
          "variation": "default",
          "primary": {
            "title": {
              "__TYPE__": "StructuredTextContent",
              "value": [
                {
                  "type": "heading1",
                  "content": {
                    "text": "Driven"
                  }
                }
              ]
            },
            "description": {
              "__TYPE__": "StructuredTextContent",
              "value": [
                {
                  "type": "paragraph",
                  "content": {
                    "text": "Quis nisi non exercitation sunt cillum anim ipsum do proident tempor dolor veniam voluptate."
                  }
                }
              ]
            }
          },
          "items": [
            {
              "__TYPE__": "GroupItemContent",
              "value": []
            }
          ]
        }
      }
    ]
  }
}